README.md
setup.py
pkit/__init__.py
pkit/__main__.py
pkit.egg-info/PKG-INFO
pkit.egg-info/SOURCES.txt
pkit.egg-info/dependency_links.txt
pkit.egg-info/entry_points.txt
pkit.egg-info/requires.txt
pkit.egg-info/top_level.txt