Metadata-Version: 2.1
Name: pkit
Version: 0.1.1
Summary: various command line utilities and scripts
Home-page: https://www.github.com/redouane/pkit
Author: Redouane Zait
Author-email: redouanezait@gmail.com
License: BSD License
Platform: UNKNOWN
Classifier: Environment :: Console
Classifier: Intended Audience :: Developers
Classifier: Intended Audience :: End Users/Desktop
Classifier: Intended Audience :: Information Technology
Classifier: Intended Audience :: System Administrators
Classifier: License :: OSI Approved :: BSD License
Classifier: Operating System :: OS Independent
Classifier: Programming Language :: Python
Classifier: Programming Language :: Python :: 3.6
Classifier: Topic :: Utilities
Provides-Extra: dev
